[
{
    "_id" : "ObjectId('62ea16b140bfad01fc021620')",
    "status" : "approved",
    "name" : "monii",
    "email" : "kajalbaisakh7@gmail.com",
    "companyid" : "9",
    "password" : "$2a$10$98YSh.wAo5xRH5MWX45y1eHH.CdClqutLpUOnCsK01wPuDUL9shae",
    "isAdmin" : "employee",
    "sequence_id" : 1,
    "createdAt" : "ISODate('2022-08-03T06:33:21.063Z')",
    "updatedAt" : "ISODate('2022-08-16T10:53:57.076Z')",
    "__v" : 0,
    "avatar" : "1660647236994bed.glb"
},
{
    "_id" : "ObjectId('62ea16f140bfad01fc021621')",
    "status" : "approved",
    "name" : "ujjwal",
    "email" : "kajalbaisakh123@gmail.com",
    "companyid" : "2",
    "password" : "$2a$10$gHOXc8iY6QD8mIm/YO5XVe43WMLV00svc5cgyFDaUGT4XoBkO0R.O",
    "isAdmin" : "employee",
    "sequence_id" : 2,
    "createdAt" : "ISODate('2022-08-03T06:34:25.532Z')",
    "updatedAt" : "ISODate('2022-10-04T17:40:13.522Z')",
    "__v" : 0
},
{
    "_id" : "ObjectId('62ea24870dc81703b03e16b0')",
    "status" : "register",
    "name" : "kajal",
    "email" : "kajalbaisakh1@gmail.com",
    "companyid" : "3",
    "password" : "$2a$10$kB87/UlQcNhpzXXAsLpw8.C9BiZnC7yj25Kd9fGgVlkeN8o4YtAIS",
    "isAdmin" : "employee",
    "sequence_id" : 3,
    "createdAt" : "ISODate('2022-08-03T07:32:23.350Z')",
    "updatedAt" : "ISODate('2022-08-03T07:32:23.350Z')",
    "__v" : 0
},
{
    "_id" : "ObjectId('62ea25f510a052197c0cf8d2')",
    "status" : "register",
    "name" : "kajal",
    "email" : "kajal@gmail.com",
    "companyid" : "4",
    "password" : "$2a$10$oIqHd9vesDWcRS3nOppeCuqjK6VWtI8ccEYYlI9wVJv/2zKbT93wO",
    "isAdmin" : "employee",
    "sequence_id" : 4,
    "createdAt" : "ISODate('2022-08-03T07:38:29.824Z')",
    "updatedAt" : "ISODate('2022-08-03T07:38:29.824Z')",
    "__v" : 0
},
{
    "_id" : "ObjectId('62ea2677452b912e24586996')",
    "status" : "register",
    "name" : "kajal",
    "email" : "kajal1@gmail.com",
    "companyid" : "5",
    "password" : "$2a$10$6tAZsLyDZ0c.NGpNcoVI4eV89VrXfKD6TOUPZPda3eFF9cWuVptyW",
    "isAdmin" : "employee",
    "sequence_id" : 5,
    "createdAt" : "ISODate('2022-08-03T07:40:39.050Z')",
    "updatedAt" : "ISODate('2022-08-03T07:40:39.050Z')",
    "__v" : 0
},
{
    "_id" : "ObjectId('62eb61089b33e32fc02ce490')",
    "status" : "register",
    "name" : "sachin",
    "email" : "sachin@gmail.com",
    "companyid" : "23",
    "password" : "$2a$10$v3.9TcS6Xj6iwBkgW.NvtuPDh5XqNE/yAI.TY/HlAEFK5qFOWTpzq",
    "isAdmin" : "employee",
    "sequence_id" : 6,
    "createdAt" : "ISODate('2022-08-04T06:02:48.022Z')",
    "updatedAt" : "ISODate('2022-08-04T06:02:48.022Z')",
    "__v" : 0
},
{
    "_id" : "ObjectId('63173228d0df9632dc7a339f')",
    "status" : "register",
    "name" : "sourav",
    "email" : "sourav@gmail.com",
    "companyid" : "wowexp1",
    "password" : "$2a$10$IKvQzWwe/gftVWBUO2SR.OYXSPtj35dhr2XfqWlfsHp5148VrVY/a",
    "isAdmin" : "employee",
    "sequence_id" : 7,
    "createdAt" : "ISODate('2022-09-06T11:42:32.727Z')",
    "updatedAt" : "ISODate('2022-09-06T11:42:32.727Z')",
    "__v" : 0
},
{
    "_id" : "ObjectId('631807b815108c0c642acf30')",
    "status" : "register",
    "name" : "john",
    "email" : "john@infotech.com",
    "companyid" : "info tech1",
    "password" : "$2a$10$/ihHhA1aL52pnkXuolfecefVVKeQpNqmb4XzPebGZ2FdNgMp5KTwO",
    "isAdmin" : "employee",
    "sequence_id" : 8,
    "createdAt" : "ISODate('2022-09-07T02:53:44.354Z')",
    "updatedAt" : "ISODate('2022-09-07T02:53:44.354Z')",
    "__v" : 0
},
{
    "_id" : "ObjectId('63185ffee131c1225cc94bd9')",
    "status" : "register",
    "name" : "kumar",
    "email" : "kumar@wowexp.com",
    "companyid" : "wowexp1",
    "password" : "$2a$10$eP9WGqhj4t2Hw17dNkY1T.upykwlNPrtmOOlZq1/yf/nB8uLpB1oy",
    "isAdmin" : "employee",
    "sequence_id" : 9,
    "createdAt" : "ISODate('2022-09-07T09:10:22.367Z')",
    "updatedAt" : "ISODate('2022-09-07T09:10:22.367Z')",
    "__v" : 0
},
{
    "_id" : "ObjectId('633c708bf775b74468251ae0')",
    "status" : "register",
    "name" : "kajal baisakh",
    "email" : "ujwal@gmail.com",
    "companyid" : "wowexp",
    "password" : "$2a$10$ZVhH9pY4emcsdURHMCTE6ObYAeDB7ZG/Ad5kKHvQ6E.BbCBZwY/xS",
    "isAdmin" : "employee",
    "sequence_id" : 10,
    "createdAt" : "ISODate('2022-10-04T17:42:35.030Z')",
    "updatedAt" : "ISODate('2022-10-04T17:42:35.030Z')",
    "__v" : 0
},
{
    "_id" : "ObjectId('633c763793f2b5182c4a61f5')",
    "status" : "register",
    "name" : "capzamin",
    "email" : "capzaminemp1@gmail.com",
    "companyid" : "capzamin1",
    "password" : "$2a$10$7da42gddUIAWCQXbZtwc7OR00xHoqNZtOcZgBDYRQRsIfXi/w8jXq",
    "isAdmin" : "employee",
    "sequence_id" : 11,
    "createdAt" : "ISODate('2022-10-04T18:06:47.928Z')",
    "updatedAt" : "ISODate('2022-10-04T18:06:47.928Z')",
    "__v" : 0
},
{
    "_id" : "ObjectId('633e7db28381b73180f5d3b7')",
    "status" : "register",
    "name" : "boxi",
    "email" : "boxi@gmail.com",
    "companyname" : "wowexp",
    "password" : "$2a$10$KVE3b63gZ9fvrfHLq7j.N.2CAMzwVtWt7E/2YUzWMq9GJvosZF6du",
    "isAdmin" : "admin",
    "createdAt" : "ISODate('2022-10-06T07:03:14.429Z')",
    "updatedAt" : "ISODate('2022-10-06T07:03:14.429Z')",
    "__v" : 0
},
{
    "_id" : "ObjectId('633ea39597c1622574e31c29')",
    "status" : "register",
    "name" : "shams",
    "email" : "shams@wowexp.com",
    "companyname" : "ifo",
    "password" : "$2a$10$DeTdMpxiUVYPlRaiPuhWZeKR8Ob8aUOR0VsTeYlo92lL1RTvCD6LG",
    "isAdmin" : "admin",
    "sequence_id" : 12,
    "createdAt" : "ISODate('2022-10-06T09:44:53.892Z')",
    "updatedAt" : "ISODate('2022-10-06T09:44:53.892Z')",
    "__v" : 0
}
]